iflow_mcp_vinayak_mehta_mcp_sonic_pi-0.1.0.dist-info/licenses/LICENSE
mcp_sonic_pi/__init__.py
mcp_sonic_pi/server.py
iflow_mcp_vinayak_mehta_mcp_sonic_pi-0.1.0.dist-info/METADATA
iflow_mcp_vinayak_mehta_mcp_sonic_pi-0.1.0.dist-info/WHEEL
iflow_mcp_vinayak_mehta_mcp_sonic_pi-0.1.0.dist-info/entry_points.txt
iflow_mcp_vinayak_mehta_mcp_sonic_pi-0.1.0.dist-info/top_level.txt
iflow_mcp_vinayak_mehta_mcp_sonic_pi-0.1.0.dist-info/RECORD
