Metadata-Version: 2.4
Name: iflow-mcp_vinayak-mehta_mcp-sonic-pi
Version: 0.1.0
Summary: MCP server for Sonic Pi
Author-email: Vinayak Mehta <vmehta94@gmail.com>
License: Apache-2.0
Project-URL: Homepage, https://github.com/vinayak-mehta/mcp-sonic-pi
Project-URL: Bug Tracker, https://github.com/vinayak-mehta/mcp-sonic-pi/issues
Classifier: Programming Language :: Python :: 3
Classifier: Programming Language :: Python :: 3.10
Classifier: Programming Language :: Python :: 3.11
Classifier: Programming Language :: Python :: 3.12
Classifier: Programming Language :: Python :: 3.13
Classifier: License :: OSI Approved :: Apache Software License
Requires-Python: >=3.10
License-File: LICENSE
Requires-Dist: mcp>=0.1.0
Requires-Dist: python-dotenv>=1.0.0
Requires-Dist: fastapi>=0.109.0
Requires-Dist: uvicorn>=0.27.0
Requires-Dist: python-osc>=1.9.3
Requires-Dist: python-sonic>=0.4.4
Requires-Dist: ruff>=0.11.2
Dynamic: license-file
